chegg/__init__.py
chegg/chegg_helpers.py
chegg/matching_pattern_collector.py
chegg/tie_breaker.py
chegg/scripts/__init__.py
chegg/scripts/main.py
chegg_marc_condon-0.0.3.dist-info/DESCRIPTION.rst
chegg_marc_condon-0.0.3.dist-info/METADATA
chegg_marc_condon-0.0.3.dist-info/RECORD
chegg_marc_condon-0.0.3.dist-info/WHEEL
chegg_marc_condon-0.0.3.dist-info/entry_points.txt
chegg_marc_condon-0.0.3.dist-info/metadata.json
chegg_marc_condon-0.0.3.dist-info/top_level.txt
