Metadata-Version: 2.0
Name: chegg-marc-condon
Version: 0.0.3
Summary: Utility Library for Taking AR report generating out of CakePHP DB
Home-page: https://github.com/fogcitymarathoner/rrg
Author: Marc Condon
Author-email: marc@sfgeek.net
License: MIT
Keywords: Chegg Code Chalenge
Platform: UNKNOWN
Classifier: Development Status :: 1 - Planning
Classifier: Intended Audience :: Developers
Classifier: Topic :: Utilities
Classifier: License :: OSI Approved :: MIT License
Classifier: Programming Language :: Python :: 2.7
Provides-Extra: dev
Requires-Dist: check-manifest; extra == 'dev'
Provides-Extra: test
Requires-Dist: coverage; extra == 'test'
